[{"id":"8dqbfc6uclnne0gs6","title":"ุทุฑุฒ ุชูู ูุงู ูพููุฑ ู ูุฑุจุงู ุขูุจุงูู","banner":"https://rezim.ir/wp-content/uploads/2022/03/2568250623c8c7dfb007e511d058fae5__charsoogh-1-819x1024.jpg","category":"ูพูุฑ","content":"\n\t\t\t\t\t\t\t\t\n\t            ูุงู ูพููุฑ ู ูุฑุจุงู ุขูุจุงูู๐๐ููู ุงุฒ ฺฏุฒููู ูุงู ุฎูุดูุฒู ุจุฑุงู ุตุจุญุงูู ู ุนุตุฑุงูู ุงุณุช,ูู ุดูุฑูู ุ ุชุฑุฏ ู ูุฐูุฐ ๐๐๐ป๐ ููุงุฏ ูุงุฒู ุจุฑุง ูุงู ูพููุฑ ู ูุฑุจุง:\n1ุจุณุชู (ุชูุฑุจุงู 227 ฺฏุฑู) ูพูุฑ ุฎุงููโุงุ ูุฑู ุดุฏู\n2 ุชฺฉู ฺฉุฑู (16 ูุงุดู ุบุฐุงุฎูุฑ)ุ ูุฑู ุดุฏู\nุฏู ููุฌุงู ุขุฑุฏ ุณููุฏ\nุดฺฉุฑ ุฏุงูู ุฑูุฒ 2 ูุงุดู ุบุฏุงุฎูุฑู\nููู 1.2 ูุงุดู ฺุงโุฎูุฑ\nููุงุฏ ูุงุฒู ุจุฑุง ุฏุงุฎู ูุงู:\nูพููุฑ ุฎุงูู ุงู ูกูฅู ฺฏุฑู\nุดูุฑ ุงูุงุดู ุบุฏุงุฎูุฑู\nูุงููู ูก/ูค ูุงุดู ฺุงูุฎูุฑู\nูุฑุจุง ุขูุจุงูู ุจู ููุฏุงุฑ ูุงุฒู\nุทุฑุฒ ุชูู\nุฏุฑ ฺฉ ฺฉุงุณู ููุงุณุจุ ูพูุฑ ุฎุงููโุง ู ฺฉุฑู ุฑุง ุชุง ุฒูุงู ฺฉู ูุฑูุ ุฑูุดู ู ูพู ฺฉุฑุฏู ุดููุฏ ูู ุจุฒูุฏ.ุขุฑุฏ ู ููฺฉ ุฑุง ุจู ุขู ุงูุฒูุฏู ู ุชุง ุฒูุงู ฺฉู ฺฉุงููุงู ุชุฑฺฉุจ ุดููุฏ ูู ุจุฒูุฏ.ุจุนุฏ ุงุฒ ุขู ุดูุฑ ุฑุง ุงุถุงูู ูููููู ุชุง ุญุงูุช ุฎููุฑู ูุทูู ูพูุฏุง ููุฏุุณูพุณ ุฎูุฑ ุฑุง ุจู ูข ูุณูุช ูุณุงูู ุชูุณู ฺฉูุฏ. ูุฑ ฺฉุฏุงู ุงุฒ ูุณูุช ูุง ุฑุง ุตุงูโฺฉุฑุฏู ู ุฑู ูุฑ ุฎูุฑ ุฑุง ุจุง ุณูููู ุจูพูุดุงูุฏ.ุจุฑุง 30 ุฏููู ุฎูุฑ ุฑุง ุฏุงุฎู ุฎฺุงู ุจฺฏุฐุงุฑุฏ.ุฏุฑ ููู ุญูุ ุจุง ุชุฑฺฉุจ ูพูุฑ ุฎุงููโุงุ ุดฺฉุฑ ุฏุงูู ุฑูุฒ ู ูุงูู ุฏุฑ ฺฉุงุณูโโุง ุฏฺฏุฑุ ูุงุฏูโุง ฺฉู ุจุฑุง ูพุฑ ฺฉุฑุฏู ุฏุงุฎู ูุงู ุงุณุช ุฑุง ุขูุงุฏู ฺฉูุฏ.ุชุง ุฒูุงู ฺฉู ุงู ููุงุฏ ุญุงูุช ุฎุงููโุง ู ูุฑู ุจฺฏุฑุฏ ูู ุจุฒูุฏ. ุณูพุณ ุขู ุฑุง ฺฉูุงุฑ ุจฺฏุฐุงุฑุฏ.ุฑู ุชุฎุชูโ ูุงุฑ ุขุฑุฏ ุจูพุงุดุฏ ู ุฎููุฑ ุฑุง 5 ุฏูููู ุฒูุฏุชุฑ ุงุฒ ูุฎฺุงู ุฏุฑุจูุงูุฑูุฏ ู ุจู ุงูุฏุงุฒู ูู ูุณุชุทูู ุจุงุฒ ูููุฏุู ุจุง ุชุฑฺฉุจ ูพูุฑ ุฎุงููโุง ู ุจุนุฏ ูุฑุจุง ุขูุจุงูู ูพุฑ ฺฉูุฏ. ู ุจุนุฏ ุฎููุฑ ุฏูู ุฑุง ูู ููููุทูุฑ ุจู ุงูุฏุงุฒู ูุณุชุทูู ุงูู ุจุงุฒ ูุฑุฏู ู ุฑูู ุฎููุฑ ฺฏุฐุงุดุชู ู ุจุนุฏ ุจุฑุด ูุงู 2 ุณุงูุชู ูุชุฑู ููุฏูู ู ุจุนุฏ ูุฑ ุจุฑุด ุฑุง ูููพูฺุงููู ุชุง ุจู ุดูู ฺฏุฑุฏ ุฏุฑ ุจูุงุฏ ู ุจุฑุง 1 ุณุงุนุช ุฏุงุฎู ุฎฺุงู ุจฺฏุฐุงุฑุฏ.ูุฑ ุฑุง ุชุง ุฏูุง 190 ุฏุฑุฌู ุณุงูุชโฺฏุฑุงุฏ ฺฏุฑูโฺฉูุฏ.ูุงู ูุง ุฑุง ุจุฑุง 10 ุชุง 11 ุฏููู ุง ุชุง ุฒูุงู ฺฉู ูุจูโูุง ุขู ููููโุง ุดููุฏ ุจูพุฒุฏ.ุณูพุณ ุจฺฏุฐุงุฑุฏ ฺฉุงููุงู ุฎูฺฉ ุดูุฏ (ูุทูุง ุจุง ฺุงู ุฏุงุบ ููุด ุฌุงุงุงู ูููู๐๐โบ๏ธ\n\t\t\t\t\t\t\t"}]